lora_lang_splitter/__init__.py
lora_lang_splitter/splitter.py
lora_lang_splitter-0.1.0.dist-info/WHEEL
lora_lang_splitter-0.1.0.dist-info/METADATA
lora_lang_splitter-0.1.0.dist-info/RECORD
